LICENSE
mltemplate/__init__.py
mltemplate/cli/__main__.py
mltemplate/pytorch_template/.dockerignore
mltemplate/pytorch_template/.flake8
mltemplate/pytorch_template/.gitignore
mltemplate/pytorch_template/Dockerfile.cpu
mltemplate/pytorch_template/Dockerfile.gpu
mltemplate/pytorch_template/LICENSE.md
mltemplate/pytorch_template/Makefile
mltemplate/pytorch_template/README.md
mltemplate/pytorch_template/__init__.py
mltemplate/pytorch_template/jupyter.sh
mltemplate/pytorch_template/pytorch_template/__init__.py
mltemplate/pytorch_template/pytorch_template/__main__.py
mltemplate/pytorch_template/pytorch_template/cli/__init__.py
mltemplate/pytorch_template/pytorch_template/cli/predict.py
mltemplate/pytorch_template/pytorch_template/cli/train.py
mltemplate/pytorch_template/pytorch_template/src/__init__.py
mltemplate/pytorch_template/pytorch_template/src/datasets.py
mltemplate/pytorch_template/pytorch_template/src/models.py
mltemplate/pytorch_template/pytorch_template/src/transforms.py
mltemplate/pytorch_template/requirements.txt
mltemplate/scripts/template.sh
mltemplate-1.0.4.dist-info/LICENSE
mltemplate-1.0.4.dist-info/METADATA
mltemplate-1.0.4.dist-info/WHEEL
mltemplate-1.0.4.dist-info/entry_points.txt
mltemplate-1.0.4.dist-info/RECORD
