Metadata-Version: 2.1
Name: mltemplate
Version: 1.0.4
Summary: Templating tool with boiler plate code for building robust machine learning projects in python.
Home-page: https://github.com/sowmyay/ml-project-template
License: MIT
Keywords: template,machine learning,pytorch,deep learning
Author: Sowmya Yellapragada
Author-email: sowmyayellapragada@gmail.com
Requires-Python: >=3.7,<4.0
Classifier: License :: OSI Approved :: MIT License
Classifier: Programming Language :: Python :: 3
Classifier: Programming Language :: Python :: 3.7
Classifier: Programming Language :: Python :: 3.8
Classifier: Programming Language :: Python :: 3.9
Classifier: Programming Language :: Python :: 3.10
Classifier: Programming Language :: Python :: 3.11
Project-URL: Repository, https://github.com/sowmyay/ml-project-template
